<ObjectDefinition>
  <information>
    <icon>none</icon>
    <description></description>
    <displayField>object_id</displayField>
    <order>0</order>
    <visibility/>
    <wfConstraintsPath></wfConstraintsPath>
    <configType>cli</configType>
    <createTemplateId></createTemplateId>
    <createTemplateObject></createTemplateObject>
    <defaultDisplay>false</defaultDisplay>
    <dynamic>false</dynamic>
    <importIfMandatoryPresent>false</importIfMandatoryPresent>
    <maxInstances>0</maxInstances>
    <relatedObjects></relatedObjects>
    <retainIfImportIsEmpty>false</retainIfImportIsEmpty>
    <name>Link Monitoring</name>
    <group>SASE|Fortinet|Fortigate</group>
    <importonce>false</importonce>
    <importrank>0</importrank>
    <reorderinstances>false</reorderinstances>
    <sortascending>false</sortascending>
    <sortauto>false</sortauto>
    <sortnumerical>false</sortnumerical>
    <sortvariable>params._order</sortvariable>
    <directoryNames>
      <directoryName>SASE</directoryName>
    </directoryNames>
  </information>
  <variables frozen="0">
    <variable displayName="Name" name="params.object_id" startIncrement="0" type="String" mandatoryArray="false" visible="true" description="" groupSeparator="" groupDisplayName="" maxLength="200" displayOrder="0" increment="0" refServiceURI="" keepOnImport="false" editable="false" uniqueItemsInDropDownList="false" onlyDetailView="false" createOnlyView="false" localVarNameMatch="" remoteVarNameMatch="" localVarToFilter="" remoteVarToFilter="" remoteVarValueToFilter="" arrayCanAdd="true" arrayCanRemove="true" arrayCanMove="true" arrayCanEdit="true" arrayMinSizeRequired="false" frozen="false" displayNameHeader="" fullDisplayName="" isCompositeKey="false" shared="false" isMandatory="true" isUserLocked="false" isEditLocked="false" isGrouped="false" isSearchable="false" isUniqueGlobal="false"/>
    <variable displayName="Interface" name="params.interface" startIncrement="0" type="ObjectRef" mandatoryArray="false" visible="true" description="" groupSeparator="" groupDisplayName="" maxLength="100" displayOrder="0" increment="0" refServiceURI="" keepOnImport="false" editable="false" uniqueItemsInDropDownList="false" onlyDetailView="false" createOnlyView="false" localVarNameMatch="" remoteVarNameMatch="" localVarToFilter="" remoteVarToFilter="" remoteVarValueToFilter="" arrayCanAdd="true" arrayCanRemove="true" arrayCanMove="true" arrayCanEdit="true" arrayMinSizeRequired="false" frozen="false" displayNameHeader="" fullDisplayName="" isCompositeKey="false" shared="false" isMandatory="false" isUserLocked="false" isEditLocked="false" isGrouped="false" isSearchable="false" isUniqueGlobal="false">
      <classes>
        <class>FortinetShowInterfaces</class>
      </classes>
    </variable>
    <variable displayName="Address Mode" name="params.addr_mode" startIncrement="0" type="String" mandatoryArray="false" visible="true" description="" groupSeparator="" groupDisplayName="" maxLength="100" displayOrder="0" increment="0" refServiceURI="" keepOnImport="false" editable="false" uniqueItemsInDropDownList="false" onlyDetailView="false" createOnlyView="false" localVarNameMatch="" remoteVarNameMatch="" localVarToFilter="" remoteVarToFilter="" remoteVarValueToFilter="" arrayCanAdd="true" arrayCanRemove="true" arrayCanMove="true" arrayCanEdit="true" arrayMinSizeRequired="false" frozen="false" displayNameHeader="" fullDisplayName="" isCompositeKey="false" shared="false" default="ipv4" isMandatory="false" isUserLocked="false" isEditLocked="false" isGrouped="false" isSearchable="false" isUniqueGlobal="false">
      <values>
        <values displayValue="ipv4">ipv4</values>
        <values displayValue="ipv6">ipv6</values>
      </values>
    </variable>
    <variable displayName="Protocol" name="params.protocol" startIncrement="0" type="String" mandatoryArray="false" visible="true" description="" groupSeparator="" groupDisplayName="" maxLength="100" displayOrder="0" increment="0" refServiceURI="" keepOnImport="false" editable="true" uniqueItemsInDropDownList="false" onlyDetailView="false" createOnlyView="false" localVarNameMatch="" remoteVarNameMatch="" localVarToFilter="" remoteVarToFilter="" remoteVarValueToFilter="" arrayCanAdd="true" arrayCanRemove="true" arrayCanMove="true" arrayCanEdit="true" arrayMinSizeRequired="false" frozen="false" displayNameHeader="" fullDisplayName="" isCompositeKey="false" shared="false" default="ping" isMandatory="true" isUserLocked="false" isEditLocked="false" isGrouped="false" isSearchable="false" isUniqueGlobal="false">
      <values>
        <values displayValue="Ping">ping</values>
      </values>
    </variable>
    <variable displayName="server" name="params.server" startIncrement="0" type="String" mandatoryArray="false" visible="true" description="" groupSeparator="" groupDisplayName="" maxLength="100" displayOrder="0" increment="0" refServiceURI="" keepOnImport="false" editable="false" uniqueItemsInDropDownList="false" onlyDetailView="false" createOnlyView="false" localVarNameMatch="" remoteVarNameMatch="" localVarToFilter="" remoteVarToFilter="" remoteVarValueToFilter="" arrayCanAdd="true" arrayCanRemove="true" arrayCanMove="true" arrayCanEdit="true" arrayMinSizeRequired="false" frozen="false" displayNameHeader="" fullDisplayName="" isCompositeKey="false" shared="false" isMandatory="false" isUserLocked="false" isEditLocked="false" isGrouped="false" isSearchable="false" isUniqueGlobal="false"/>
    <variable displayName="Source IP" name="params.source_ip" startIncrement="0" type="Composite" mandatoryArray="false" visible="true" description="" groupSeparator="" groupDisplayName="" maxLength="100" displayOrder="14" increment="0" refServiceURI="" keepOnImport="false" editable="false" uniqueItemsInDropDownList="false" onlyDetailView="false" createOnlyView="false" localVarNameMatch="" remoteVarNameMatch="" localVarToFilter="" remoteVarToFilter="" remoteVarValueToFilter="" arrayCanAdd="true" arrayCanRemove="true" arrayCanMove="true" arrayCanEdit="true" arrayMinSizeRequired="false" frozen="false" selector="params.addr_mode" displayNameHeader="" fullDisplayName="" isCompositeKey="false" shared="false" isMandatory="false" isUserLocked="false" isEditLocked="false" isGrouped="false" isSearchable="false" isUniqueGlobal="false">
      <behaviors>
        <behaviour arrayCanAdd="true" arrayCanRemove="true" arrayCanMove="true" arrayCanEdit="true" editable="false" visible="true" displayName="Source IP" displayOrder="14" maxLength="130" isMandatory="false" isUserLocked="false" name="params.source_ip" selectorValue="ipv4" startIncrement="0" type="IpAddress" default="0.0.0.0" localVarToFilter="" remoteVarToFilter="" uniqueItemsInDropDownList="false">
          <compositeKey>false</compositeKey>
          <codeLanguage></codeLanguage>
          <defaultValueLong/>
          <description></description>
          <displayNameHeader></displayNameHeader>
          <fullDisplayName></fullDisplayName>
          <groupDisplayName></groupDisplayName>
          <groupSeparator></groupSeparator>
          <isGrouped>false</isGrouped>
          <increment>0</increment>
          <isCompositeKey>false</isCompositeKey>
          <keepOnImport>false</keepOnImport>
          <mandatoryArray>false</mandatoryArray>
          <onlyDetailView>false</onlyDetailView>
          <refDeviceIdVar></refDeviceIdVar>
          <refServiceURI></refServiceURI>
          <isSearchable>false</isSearchable>
          <selector></selector>
          <isUniqueGlobal>false</isUniqueGlobal>
        </behaviour>
        <behaviour arrayCanAdd="true" arrayCanRemove="true" arrayCanMove="true" arrayCanEdit="true" editable="false" visible="false" displayName="Source IP" displayOrder="14" maxLength="130" isMandatory="false" isUserLocked="false" name="params.source_ip" selectorValue="ipv6" startIncrement="0" type="IpAddress" default="0.0.0.0" localVarToFilter="" remoteVarToFilter="" uniqueItemsInDropDownList="false">
          <compositeKey>false</compositeKey>
          <codeLanguage></codeLanguage>
          <defaultValueLong/>
          <description></description>
          <displayNameHeader></displayNameHeader>
          <fullDisplayName></fullDisplayName>
          <groupDisplayName></groupDisplayName>
          <groupSeparator></groupSeparator>
          <isGrouped>false</isGrouped>
          <increment>0</increment>
          <isCompositeKey>false</isCompositeKey>
          <keepOnImport>false</keepOnImport>
          <mandatoryArray>false</mandatoryArray>
          <onlyDetailView>false</onlyDetailView>
          <refDeviceIdVar></refDeviceIdVar>
          <refServiceURI></refServiceURI>
          <isSearchable>false</isSearchable>
          <selector></selector>
          <isUniqueGlobal>false</isUniqueGlobal>
        </behaviour>
      </behaviors>
    </variable>
    <variable displayName="Gateway IP" name="params.gateway_ip" startIncrement="0" type="Composite" mandatoryArray="false" visible="true" description="" groupSeparator="" groupDisplayName="" maxLength="100" displayOrder="0" increment="0" refServiceURI="" keepOnImport="false" editable="false" uniqueItemsInDropDownList="false" onlyDetailView="false" createOnlyView="false" localVarNameMatch="" remoteVarNameMatch="" localVarToFilter="" remoteVarToFilter="" remoteVarValueToFilter="" arrayCanAdd="true" arrayCanRemove="true" arrayCanMove="true" arrayCanEdit="true" arrayMinSizeRequired="false" frozen="false" selector="params.addr_mode" displayNameHeader="" fullDisplayName="" isCompositeKey="false" shared="false" isMandatory="false" isUserLocked="false" isEditLocked="false" isGrouped="false" isSearchable="false" isUniqueGlobal="false">
      <behaviors>
        <behaviour arrayCanAdd="true" arrayCanRemove="true" arrayCanMove="true" arrayCanEdit="true" editable="false" visible="true" displayName="gateway_ip" displayOrder="0" maxLength="130" isMandatory="false" isUserLocked="false" name="params.gateway_ip" selectorValue="ipv4" startIncrement="0" type="IpAddress" default="0.0.0.0" localVarToFilter="" remoteVarToFilter="" uniqueItemsInDropDownList="false">
          <compositeKey>false</compositeKey>
          <codeLanguage></codeLanguage>
          <defaultValueLong/>
          <description></description>
          <displayNameHeader></displayNameHeader>
          <fullDisplayName></fullDisplayName>
          <groupDisplayName></groupDisplayName>
          <groupSeparator></groupSeparator>
          <isGrouped>false</isGrouped>
          <increment>0</increment>
          <isCompositeKey>false</isCompositeKey>
          <keepOnImport>false</keepOnImport>
          <mandatoryArray>false</mandatoryArray>
          <onlyDetailView>false</onlyDetailView>
          <refDeviceIdVar></refDeviceIdVar>
          <refServiceURI></refServiceURI>
          <isSearchable>false</isSearchable>
          <selector></selector>
          <isUniqueGlobal>false</isUniqueGlobal>
        </behaviour>
        <behaviour arrayCanAdd="true" arrayCanRemove="true" arrayCanMove="true" arrayCanEdit="true" editable="false" visible="false" displayName="gateway_ip" displayOrder="0" maxLength="130" isMandatory="false" isUserLocked="false" name="params.gateway_ip" selectorValue="ipv6" startIncrement="0" type="IpAddress" default="0.0.0.0" localVarToFilter="" remoteVarToFilter="" uniqueItemsInDropDownList="false">
          <compositeKey>false</compositeKey>
          <codeLanguage></codeLanguage>
          <defaultValueLong/>
          <description></description>
          <displayNameHeader></displayNameHeader>
          <fullDisplayName></fullDisplayName>
          <groupDisplayName></groupDisplayName>
          <groupSeparator></groupSeparator>
          <isGrouped>false</isGrouped>
          <increment>0</increment>
          <isCompositeKey>false</isCompositeKey>
          <keepOnImport>false</keepOnImport>
          <mandatoryArray>false</mandatoryArray>
          <onlyDetailView>false</onlyDetailView>
          <refDeviceIdVar></refDeviceIdVar>
          <refServiceURI></refServiceURI>
          <isSearchable>false</isSearchable>
          <selector></selector>
          <isUniqueGlobal>false</isUniqueGlobal>
        </behaviour>
      </behaviors>
    </variable>
    <variable displayName="Source IP v6" name="params.source_ip6" startIncrement="0" type="Composite" mandatoryArray="false" visible="true" description="" groupSeparator="" groupDisplayName="" maxLength="100" displayOrder="13" increment="0" refServiceURI="" keepOnImport="false" editable="false" uniqueItemsInDropDownList="false" onlyDetailView="false" createOnlyView="false" localVarNameMatch="" remoteVarNameMatch="" localVarToFilter="" remoteVarToFilter="" remoteVarValueToFilter="" arrayCanAdd="true" arrayCanRemove="true" arrayCanMove="true" arrayCanEdit="true" arrayMinSizeRequired="false" frozen="false" selector="params.addr_mode" displayNameHeader="" fullDisplayName="" isCompositeKey="false" shared="false" isMandatory="false" isUserLocked="false" isEditLocked="false" isGrouped="false" isSearchable="false" isUniqueGlobal="false">
      <behaviors>
        <behaviour arrayCanAdd="true" arrayCanRemove="true" arrayCanMove="true" arrayCanEdit="true" editable="false" visible="false" displayName="Source IP v6" displayOrder="13" maxLength="100" isMandatory="false" isUserLocked="false" name="params.source_ip6" selectorValue="ipv4" startIncrement="0" type="Ipv6Address" default="::" localVarToFilter="" remoteVarToFilter="" uniqueItemsInDropDownList="false">
          <compositeKey>false</compositeKey>
          <codeLanguage></codeLanguage>
          <defaultValueLong/>
          <description></description>
          <displayNameHeader></displayNameHeader>
          <fullDisplayName></fullDisplayName>
          <groupDisplayName></groupDisplayName>
          <groupSeparator></groupSeparator>
          <isGrouped>false</isGrouped>
          <increment>0</increment>
          <isCompositeKey>false</isCompositeKey>
          <keepOnImport>false</keepOnImport>
          <mandatoryArray>false</mandatoryArray>
          <onlyDetailView>false</onlyDetailView>
          <refDeviceIdVar></refDeviceIdVar>
          <refServiceURI></refServiceURI>
          <isSearchable>false</isSearchable>
          <selector></selector>
          <isUniqueGlobal>false</isUniqueGlobal>
        </behaviour>
        <behaviour arrayCanAdd="true" arrayCanRemove="true" arrayCanMove="true" arrayCanEdit="true" editable="false" visible="true" displayName="Source IP v6" displayOrder="13" maxLength="100" isMandatory="false" isUserLocked="false" name="params.source_ip6" selectorValue="ipv6" startIncrement="0" type="Ipv6Address" default="::" localVarToFilter="" remoteVarToFilter="" uniqueItemsInDropDownList="false">
          <compositeKey>false</compositeKey>
          <codeLanguage></codeLanguage>
          <defaultValueLong/>
          <description></description>
          <displayNameHeader></displayNameHeader>
          <fullDisplayName></fullDisplayName>
          <groupDisplayName></groupDisplayName>
          <groupSeparator></groupSeparator>
          <isGrouped>false</isGrouped>
          <increment>0</increment>
          <isCompositeKey>false</isCompositeKey>
          <keepOnImport>false</keepOnImport>
          <mandatoryArray>false</mandatoryArray>
          <onlyDetailView>false</onlyDetailView>
          <refDeviceIdVar></refDeviceIdVar>
          <refServiceURI></refServiceURI>
          <isSearchable>false</isSearchable>
          <selector></selector>
          <isUniqueGlobal>false</isUniqueGlobal>
        </behaviour>
      </behaviors>
    </variable>
    <variable displayName="Gateway ipV6" name="params.gateway_ip6" startIncrement="0" type="Composite" mandatoryArray="false" visible="true" description="" groupSeparator="" groupDisplayName="" maxLength="100" displayOrder="0" increment="0" refServiceURI="" keepOnImport="false" editable="false" uniqueItemsInDropDownList="false" onlyDetailView="false" createOnlyView="false" localVarNameMatch="" remoteVarNameMatch="" localVarToFilter="" remoteVarToFilter="" remoteVarValueToFilter="" arrayCanAdd="true" arrayCanRemove="true" arrayCanMove="true" arrayCanEdit="true" arrayMinSizeRequired="false" frozen="false" selector="params.addr_mode" displayNameHeader="" fullDisplayName="" isCompositeKey="false" shared="false" isMandatory="false" isUserLocked="false" isEditLocked="false" isGrouped="false" isSearchable="false" isUniqueGlobal="false">
      <behaviors>
        <behaviour arrayCanAdd="true" arrayCanRemove="true" arrayCanMove="true" arrayCanEdit="true" editable="false" visible="false" displayName="gateway_ip6" displayOrder="0" maxLength="100" isMandatory="false" isUserLocked="false" name="params.gateway_ip6" selectorValue="ipv4" startIncrement="0" type="Ipv6Address" default="::" localVarToFilter="" remoteVarToFilter="" uniqueItemsInDropDownList="false">
          <compositeKey>false</compositeKey>
          <codeLanguage></codeLanguage>
          <defaultValueLong/>
          <description></description>
          <displayNameHeader></displayNameHeader>
          <fullDisplayName></fullDisplayName>
          <groupDisplayName></groupDisplayName>
          <groupSeparator></groupSeparator>
          <isGrouped>false</isGrouped>
          <increment>0</increment>
          <isCompositeKey>false</isCompositeKey>
          <keepOnImport>false</keepOnImport>
          <mandatoryArray>false</mandatoryArray>
          <onlyDetailView>false</onlyDetailView>
          <refDeviceIdVar></refDeviceIdVar>
          <refServiceURI></refServiceURI>
          <isSearchable>false</isSearchable>
          <selector></selector>
          <isUniqueGlobal>false</isUniqueGlobal>
        </behaviour>
        <behaviour arrayCanAdd="true" arrayCanRemove="true" arrayCanMove="true" arrayCanEdit="true" editable="false" visible="true" displayName="gateway_ip6" displayOrder="0" maxLength="100" isMandatory="false" isUserLocked="false" name="params.gateway_ip6" selectorValue="ipv6" startIncrement="0" type="Ipv6Address" default="::" localVarToFilter="" remoteVarToFilter="" uniqueItemsInDropDownList="false">
          <compositeKey>false</compositeKey>
          <codeLanguage></codeLanguage>
          <defaultValueLong/>
          <description></description>
          <displayNameHeader></displayNameHeader>
          <fullDisplayName></fullDisplayName>
          <groupDisplayName></groupDisplayName>
          <groupSeparator></groupSeparator>
          <isGrouped>false</isGrouped>
          <increment>0</increment>
          <isCompositeKey>false</isCompositeKey>
          <keepOnImport>false</keepOnImport>
          <mandatoryArray>false</mandatoryArray>
          <onlyDetailView>false</onlyDetailView>
          <refDeviceIdVar></refDeviceIdVar>
          <refServiceURI></refServiceURI>
          <isSearchable>false</isSearchable>
          <selector></selector>
          <isUniqueGlobal>false</isUniqueGlobal>
        </behaviour>
      </behaviors>
    </variable>
    <variable displayName="Interval" name="params.interval" startIncrement="0" type="Integer" mandatoryArray="false" visible="true" description="" groupSeparator="" groupDisplayName="" maxLength="100" displayOrder="0" increment="0" refServiceURI="" keepOnImport="false" editable="false" uniqueItemsInDropDownList="false" onlyDetailView="false" createOnlyView="false" localVarNameMatch="" remoteVarNameMatch="" localVarToFilter="" remoteVarToFilter="" remoteVarValueToFilter="" arrayCanAdd="true" arrayCanRemove="true" arrayCanMove="true" arrayCanEdit="true" arrayMinSizeRequired="false" frozen="false" displayNameHeader="" fullDisplayName="" isCompositeKey="false" shared="false" default="500" isMandatory="true" isUserLocked="false" isEditLocked="false" isGrouped="false" isSearchable="false" isUniqueGlobal="false"/>
    <variable displayName="Fail Time" name="params.failtime" startIncrement="0" type="Integer" mandatoryArray="false" visible="true" description="" groupSeparator="" groupDisplayName="" maxLength="100" displayOrder="0" increment="0" refServiceURI="" keepOnImport="false" editable="false" uniqueItemsInDropDownList="false" onlyDetailView="false" createOnlyView="false" localVarNameMatch="" remoteVarNameMatch="" localVarToFilter="" remoteVarToFilter="" remoteVarValueToFilter="" arrayCanAdd="true" arrayCanRemove="true" arrayCanMove="true" arrayCanEdit="true" arrayMinSizeRequired="false" frozen="false" displayNameHeader="" fullDisplayName="" isCompositeKey="false" shared="false" default="5" isMandatory="true" isUserLocked="false" isEditLocked="false" isGrouped="false" isSearchable="false" isUniqueGlobal="false"/>
    <variable displayName="Recovery Time" name="params.recoverytime" startIncrement="0" type="Integer" mandatoryArray="false" visible="true" description="" groupSeparator="" groupDisplayName="" maxLength="100" displayOrder="0" increment="0" refServiceURI="" keepOnImport="false" editable="false" uniqueItemsInDropDownList="false" onlyDetailView="false" createOnlyView="false" localVarNameMatch="" remoteVarNameMatch="" localVarToFilter="" remoteVarToFilter="" remoteVarValueToFilter="" arrayCanAdd="true" arrayCanRemove="true" arrayCanMove="true" arrayCanEdit="true" arrayMinSizeRequired="false" frozen="false" displayNameHeader="" fullDisplayName="" isCompositeKey="false" shared="false" default="5" isMandatory="true" isUserLocked="false" isEditLocked="false" isGrouped="false" isSearchable="false" isUniqueGlobal="false"/>
    <variable displayName="HA Priority" name="params.ha_priority" startIncrement="0" type="Integer" mandatoryArray="false" visible="true" description="" groupSeparator="" groupDisplayName="" maxLength="100" displayOrder="0" increment="0" refServiceURI="" keepOnImport="false" editable="false" uniqueItemsInDropDownList="false" onlyDetailView="false" createOnlyView="false" localVarNameMatch="" remoteVarNameMatch="" localVarToFilter="" remoteVarToFilter="" remoteVarValueToFilter="" arrayCanAdd="true" arrayCanRemove="true" arrayCanMove="true" arrayCanEdit="true" arrayMinSizeRequired="false" frozen="false" displayNameHeader="" fullDisplayName="" isCompositeKey="false" shared="false" default="1" isMandatory="false" isUserLocked="false" isEditLocked="false" isGrouped="false" isSearchable="false" isUniqueGlobal="false"/>
    <variable displayName="Update Cascade Interface" name="params.update_cascade_interface" startIncrement="0" type="String" mandatoryArray="false" visible="true" description="" groupSeparator="" groupDisplayName="" maxLength="100" displayOrder="0" increment="0" refServiceURI="" keepOnImport="false" editable="false" uniqueItemsInDropDownList="false" onlyDetailView="false" createOnlyView="false" localVarNameMatch="" remoteVarNameMatch="" localVarToFilter="" remoteVarToFilter="" remoteVarValueToFilter="" arrayCanAdd="true" arrayCanRemove="true" arrayCanMove="true" arrayCanEdit="true" arrayMinSizeRequired="false" frozen="false" displayNameHeader="" fullDisplayName="" isCompositeKey="false" shared="false" default="enable" isMandatory="false" isUserLocked="false" isEditLocked="false" isGrouped="false" isSearchable="false" isUniqueGlobal="false">
      <values>
        <values displayValue="Enable">enable</values>
        <values displayValue="Disable">disable</values>
      </values>
    </variable>
    <variable displayName="Update Static Route" name="params.update_static_route" startIncrement="0" type="String" mandatoryArray="false" visible="true" description="" groupSeparator="" groupDisplayName="" maxLength="100" displayOrder="0" increment="0" refServiceURI="" keepOnImport="false" editable="false" uniqueItemsInDropDownList="false" onlyDetailView="false" createOnlyView="false" localVarNameMatch="" remoteVarNameMatch="" localVarToFilter="" remoteVarToFilter="" remoteVarValueToFilter="" arrayCanAdd="true" arrayCanRemove="true" arrayCanMove="true" arrayCanEdit="true" arrayMinSizeRequired="false" frozen="false" displayNameHeader="" fullDisplayName="" isCompositeKey="false" shared="false" default="enable" isMandatory="false" isUserLocked="false" isEditLocked="false" isGrouped="false" isSearchable="false" isUniqueGlobal="false">
      <values>
        <values displayValue="Enable">enable</values>
        <values displayValue="Disable">disable</values>
      </values>
    </variable>
    <variable displayName="Status" name="params.status" startIncrement="0" type="String" mandatoryArray="false" visible="true" description="" groupSeparator="" groupDisplayName="" maxLength="100" displayOrder="0" increment="0" refServiceURI="" keepOnImport="false" editable="false" uniqueItemsInDropDownList="false" onlyDetailView="false" createOnlyView="false" localVarNameMatch="" remoteVarNameMatch="" localVarToFilter="" remoteVarToFilter="" remoteVarValueToFilter="" arrayCanAdd="true" arrayCanRemove="true" arrayCanMove="true" arrayCanEdit="true" arrayMinSizeRequired="false" frozen="false" displayNameHeader="" fullDisplayName="" isCompositeKey="false" shared="false" default="enable" isMandatory="false" isUserLocked="false" isEditLocked="false" isGrouped="false" isSearchable="false" isUniqueGlobal="false">
      <values>
        <values displayValue="Enable">enable</values>
        <values displayValue="Disable">disable</values>
      </values>
    </variable>
  </variables>
  <example>
    <content>config system link-monitor
    edit &quot;test_Pierre&quot;
        set addr-mode ipv4
        set srcintf &quot;Tunnel13&quot;
        set server &quot;9.9.9.9&quot;
        set protocol ping
        set gateway-ip 0.0.0.0
        set source-ip 81.1.3.116
        set interval 500
        set failtime 5
        set recoverytime 5
        set ha-priority 1
        set update-cascade-interface enable
        set update-static-route enable
        set status enable
    next
    edit &quot;blabla&quot;
        set addr-mode ipv4
        set srcintf &quot;Tunnel12&quot;
        set server &quot;10.10.11.12&quot;
        set protocol ping
        set gateway-ip 0.0.0.0
        set source-ip 0.0.0.0
        set interval 500
        set failtime 5
        set recoverytime 5
        set ha-priority 1
        set update-cascade-interface enable
        set update-static-route enable
        set status enable
    next
    edit &quot;test_Pierre2&quot;
        set addr-mode ipv4
        set srcintf &quot;port1&quot;
        set server &quot;10.10.11.14&quot;
        set protocol ping
        set gateway-ip 0.0.0.0
        set source-ip 0.0.0.0
        set interval 500
        set failtime 5
        set recoverytime 5
        set ha-priority 1
        set update-cascade-interface enable
        set update-static-route enable
        set status enable
    next
end</content>
  </example>
  <command name="IMPORT">
    <operation><![CDATA[config system link-monitor##show full-configuration##end]]></operation>
    <parser>
      <section>
        <regexp>@edit &quot;(?&lt;object_id&gt;.*)&quot;@</regexp>
      </section>
      <lines>
        <line>
          <regexp>@set addr-mode (?&lt;addr_mode&gt;\S+)@</regexp>
          <xpath></xpath>
        </line>
        <line>
          <regexp>@set srcintf &quot;(?&lt;interface&gt;\S+)&quot;@</regexp>
          <xpath></xpath>
        </line>
        <line>
          <regexp></regexp>
          <xpath></xpath>
        </line>
        <line>
          <regexp></regexp>
          <xpath></xpath>
        </line>
        <line>
          <regexp></regexp>
          <xpath></xpath>
        </line>
        <line>
          <regexp></regexp>
          <xpath></xpath>
        </line>
        <line>
          <regexp></regexp>
          <xpath></xpath>
        </line>
        <line>
          <regexp>@set interval (?&lt;interval&gt;\d+)@</regexp>
          <xpath></xpath>
        </line>
        <line>
          <regexp>@set failtime (?&lt;failtime&gt;\d+)@</regexp>
          <xpath></xpath>
        </line>
        <line>
          <regexp>@set recoverytime (?&lt;recoverytime&gt;\d+)@</regexp>
          <xpath></xpath>
        </line>
        <line>
          <regexp>@set source-ip (?&lt;source_ip&gt;\S+)@</regexp>
          <xpath></xpath>
        </line>
        <line>
          <regexp>@set source-ip6 (?&lt;source_ip6&gt;\S+)@</regexp>
          <xpath></xpath>
        </line>
        <line>
          <regexp>@set gateway-ip (?&lt;gateway_ip&gt;\S+)@</regexp>
          <xpath></xpath>
        </line>
        <line>
          <regexp>@set gateway-ip6 (?&lt;gateway_ip6&gt;\S+)@</regexp>
          <xpath></xpath>
        </line>
        <line>
          <regexp>@set ha-priority (?&lt;ha_priority&gt;\d+)@</regexp>
          <xpath></xpath>
        </line>
        <line>
          <regexp></regexp>
          <xpath></xpath>
        </line>
        <line>
          <regexp></regexp>
          <xpath></xpath>
        </line>
        <line>
          <regexp></regexp>
          <xpath></xpath>
        </line>
        <line>
          <regexp>@set server &quot;(?&lt;server&gt;\S+)&quot;@</regexp>
          <xpath></xpath>
        </line>
        <line>
          <regexp>@set protocol (?&lt;protocol&gt;\S+)@</regexp>
          <xpath></xpath>
        </line>
        <line>
          <regexp>@set update-cascade-interface (?&lt;update_cascade_interface&gt;\S+)@</regexp>
          <xpath></xpath>
        </line>
        <line>
          <regexp>@set update-static-route (?&lt;update_static_route&gt;\S+)$@</regexp>
          <xpath></xpath>
        </line>
        <line>
          <regexp>@set status (?&lt;status&gt;\S+)$@</regexp>
          <xpath></xpath>
        </line>
        <ignore>
          <regexp>@config@</regexp>
        </ignore>
        <ignore>
          <regexp>@next$@</regexp>
        </ignore>
        <ignore>
          <regexp>@end$@</regexp>
        </ignore>
        <ignore>
          <regexp>@set@</regexp>
        </ignore>
      </lines>
    </parser>
  </command>
  <command name="CREATE">
    <operation><![CDATA[config system link-monitor
    edit "{$params.object_id}"
        set addr-mode {$params.addr_mode}
        set srcintf "{$params.interface}"
        set protocol {$params.protocol}
        set server "{$params.server}"
        {if $params.addr_mode eq "ipv4"}
        {if $params.gateway_ip neq ""} 
        set gateway-ip {$params.gateway_ip}
        {/if}
        {if $params.source_ip neq ""} 
        set source-ip {$params.source_ip}
        {/if}
        {/if}
        {if $params.addr_mode eq "ipv6"}
        {if $params.gateway_ip6 neq ""} 
        set gateway-ip6 {$params.gateway_ip6}
        {/if}
        {if $params.source_ip6 neq ""} 
        set source-ip6 {$params.source_ip6}
        {/if}
        {/if}
        
        set interval {$params.interval}
        set failtime {$params.failtime}
        set recoverytime {$params.recoverytime}
        set ha-priority {$params.ha_priority}
        set update-cascade-interface enable
        set update-static-route enable
        set status enable
    next
end]]></operation>
  </command>
  <command name="READ"/>
  <command name="UPDATE">
    <operation><![CDATA[config system link-monitor
    edit "{$params.object_id}"
        set addr-mode {$params.addr_mode}
        set srcintf "{$params.interface}"
        set protocol {$params.protocol}
        set server "{$params.server}"
        {if $params.addr_mode eq "ipv4"}
        {if $params.gateway_ip neq ""} 
        set gateway-ip {$params.gateway_ip}
        {/if}
        {if $params.source_ip neq ""} 
        set source-ip {$params.source_ip}
        {/if}
        {/if}
        {if $params.addr_mode eq "ipv6"}
        {if $params.gateway_ip6 neq ""} 
        set gateway-ip6 {$params.gateway_ip6}
        {/if}
        {if $params.source_ip6 neq ""} 
        set source-ip6 {$params.source_ip6}
        {/if}
        {/if}
        
        set interval {$params.interval}
        set failtime {$params.failtime}
        set recoverytime {$params.recoverytime}
        set ha-priority {$params.ha_priority}
        set update-cascade-interface enable
        set update-static-route enable
        set status enable
    next
end]]></operation>
  </command>
  <command name="CONSTRAINT"/>
  <command name="DELETE">
    <operation><![CDATA[config system link-monitor
    delete "{$params.object_id}"
end]]></operation>
  </command>
  <command name="LIST"/>
  <displayName>Link Monitoring</displayName>
  <order>0</order>
</ObjectDefinition>
